api_key_factory/__init__.py
api_key_factory/__init__.pyi
api_key_factory/api_key_factory.py
api_key_factory/factory.pyi
api_key_factory/util.pyi
api_key_factory/factory/__init__.py
api_key_factory/factory/__init__.pyi
api_key_factory/factory/key.py
api_key_factory/factory/key.pyi
api_key_factory/util/__init__.py
api_key_factory/util/__init__.pyi
api_key_factory/util/dir.py
api_key_factory/util/dir.pyi
api_key_factory/util/file.py
api_key_factory/util/file.pyi
api_key_factory-1.3.12.dist-info/METADATA
api_key_factory-1.3.12.dist-info/WHEEL
api_key_factory-1.3.12.dist-info/entry_points.txt
api_key_factory-1.3.12.dist-info/licenses/LICENSE
api_key_factory-1.3.12.dist-info/RECORD
