Metadata-Version: 2.4
Name: api-key-factory
Version: 1.3.12
Summary: A simple CLI tool to generate API Key
Project-URL: Homepage, https://gitlab.com/op_so/projects/api-key-factory
Project-URL: Documentation, https://op_so.gitlab.io/projects/api-key-factory
Author-email: FX Soubirou <soubirou@yahoo.fr>
License: MIT
License-File: LICENSE
Classifier: License :: OSI Approved :: MIT License
Classifier: Operating System :: OS Independent
Classifier: Programming Language :: Python :: 3
Requires-Python: >=3.13
Requires-Dist: click==8.3.1
Requires-Dist: pydantic==2.12.4
